wsgi_listener/__init__.py
wsgi_listener/formatters.py
wsgi_listener/timehacks.py
wsgi_listener-0.1.dist-info/LICENSE
wsgi_listener-0.1.dist-info/WHEEL
wsgi_listener-0.1.dist-info/METADATA
wsgi_listener-0.1.dist-info/RECORD
